rekishikon/__init__.py
rekishikon/detector.py
rekishikon/detector_factory.py
rekishikon/lang_detect_exception.py
rekishikon/language.py
rekishikon/profiles/af
rekishikon/profiles/ar
rekishikon/profiles/bg
rekishikon/profiles/bn
rekishikon/profiles/ca
rekishikon/profiles/cs
rekishikon/profiles/cy
rekishikon/profiles/da
rekishikon/profiles/de
rekishikon/profiles/el
rekishikon/profiles/en
rekishikon/profiles/es
rekishikon/profiles/et
rekishikon/profiles/fa
rekishikon/profiles/fi
rekishikon/profiles/fr
rekishikon/profiles/gu
rekishikon/profiles/he
rekishikon/profiles/hi
rekishikon/profiles/hr
rekishikon/profiles/hu
rekishikon/profiles/id
rekishikon/profiles/ig
rekishikon/profiles/it
rekishikon/profiles/ja
rekishikon/profiles/kn
rekishikon/profiles/ko
rekishikon/profiles/lt
rekishikon/profiles/lv
rekishikon/profiles/mk
rekishikon/profiles/ml
rekishikon/profiles/mr
rekishikon/profiles/ne
rekishikon/profiles/nl
rekishikon/profiles/no
rekishikon/profiles/pa
rekishikon/profiles/pl
rekishikon/profiles/pt
rekishikon/profiles/ro
rekishikon/profiles/ru
rekishikon/profiles/sk
rekishikon/profiles/sl
rekishikon/profiles/so
rekishikon/profiles/sq
rekishikon/profiles/sv
rekishikon/profiles/ta
rekishikon/profiles/te
rekishikon/profiles/th
rekishikon/profiles/tl
rekishikon/profiles/tr
rekishikon/profiles/uk
rekishikon/profiles/ur
rekishikon/profiles/zh-cn
rekishikon/profiles/zh-tw
rekishikon/utils/__init__.py
rekishikon/utils/generate_profile.py
rekishikon/utils/lang_profile.py
rekishikon/utils/messages.properties
rekishikon/utils/messages.py
rekishikon/utils/ngram.py
rekishikon/utils/unicode_block.py
rekishikon-0.3.2.dist-info/WHEEL
rekishikon-0.3.2.dist-info/METADATA
rekishikon-0.3.2.dist-info/RECORD
